<customapi uniquename="dgt_run_carrier_constraints_check">
  <allowedcustomprocessingsteptype>2</allowedcustomprocessingsteptype>
  <bindingtype>1</bindingtype>
  <boundentitylogicalname>dgt_workbench</boundentitylogicalname>
  <description default="Run Carrier Constraints Check">
    <label description="Run Carrier Constraints Check" languagecode="1033" />
  </description>
  <displayname default="Run Carrier Constraints Check">
    <label description="Run Carrier Constraints Check" languagecode="1033" />
  </displayname>
  <iscustomizable>1</iscustomizable>
  <isfunction>0</isfunction>
  <isprivate>0</isprivate>
  <name>Run Carrier Constraints Check</name>
  <plugintypeid>
    <plugintypeexportkey>aba61850-c536-ef11-8409-000d3aa8c88e</plugintypeexportkey>
  </plugintypeid>
  <workflowsdkstepenabled>1</workflowsdkstepenabled>
</customapi>