<?xml version="1.0" encoding="utf-8"?>
<optionset Name="dgt_log_level_set" localizedName="Log Level" xmlns:xsi="http://www.w3.org/2001/XMLSchema-instance">
  <OptionSetType>picklist</OptionSetType>
  <IsGlobal>1</IsGlobal>
  <IntroducedVersion>3.0.1.0</IntroducedVersion>
  <IsCustomizable>1</IsCustomizable>
  <ExternalTypeName></ExternalTypeName>
  <displaynames>
    <displayname description="Log Level" languagecode="1033" />
  </displaynames>
  <Descriptions>
    <Description description="" languagecode="1033" />
  </Descriptions>
  <options>
    <option value="283510000" ExternalValue="" Color="#f08080">
      <labels>
        <label description="0 - Error" languagecode="1033" />
      </labels>
      <Descriptions>
        <Description description="" languagecode="1033" />
      </Descriptions>
    </option>
    <option value="283510001" ExternalValue="" Color="#f4faa0">
      <labels>
        <label description="1 - Warning" languagecode="1033" />
      </labels>
      <Descriptions>
        <Description description="" languagecode="1033" />
      </Descriptions>
    </option>
    <option value="283510002" ExternalValue="" Color="#a9a9e9">
      <labels>
        <label description="2 - Information" languagecode="1033" />
      </labels>
      <Descriptions>
        <Description description="" languagecode="1033" />
      </Descriptions>
    </option>
    <option value="283510003" ExternalValue="" Color="#dcdcdc">
      <labels>
        <label description="3 - Debug" languagecode="1033" />
      </labels>
      <Descriptions>
        <Description description="" languagecode="1033" />
      </Descriptions>
    </option>
  </options>
</optionset>